MANIFEST.in
requirements.txt
setup.py
db_op_abstractions/__init__.py
db_op_abstractions/mysql.py
db_op_abstractions/pg.py
db_op_abstractions.egg-info/PKG-INFO
db_op_abstractions.egg-info/SOURCES.txt
db_op_abstractions.egg-info/dependency_links.txt
db_op_abstractions.egg-info/not-zip-safe
db_op_abstractions.egg-info/requires.txt
db_op_abstractions.egg-info/top_level.txt