Metadata-Version: 1.0
Name: db-op-abstractions
Version: 0.5.0
Summary: Contains higher level operation functions for MySQL, PG, Redshift, etc.
Home-page: https://github.com/tommyjcarpenter/db-op-abstractions
Author: Tommy Carpenter, Michael Hwang
Author-email: UNKNOWN
License: UNKNOWN
Platform: UNKNOWN
